cc_utils/__about__.py
cc_utils/__init__.py
cc_utils/flask_logging_ext.py
cc_utils/flask_utils.py
ccrab_utils-0.0.9.dist-info/METADATA
ccrab_utils-0.0.9.dist-info/WHEEL
ccrab_utils-0.0.9.dist-info/top_level.txt
ccrab_utils-0.0.9.dist-info/RECORD
