Metadata-Version: 2.1
Name: ccrab-utils
Version: 0.0.9
Summary: utilities
Home-page: UNKNOWN
Author: John Pickerill
Author-email: john@curiouscrab.com
License: MIT
Platform: any
Classifier: Development Status :: 4 - Beta
Classifier: Environment :: Web Environment
Classifier: Intended Audience :: Developers
Classifier: License :: OSI Approved :: BSD License
Classifier: Operating System :: OS Independent
Classifier: Programming Language :: Python :: 3.5
Classifier: Programming Language :: Python :: Implementation :: PyPy
Classifier: Topic :: Software Development :: Libraries :: Python Modules
Requires-Dist: pyyaml (>=5.1)
Requires-Dist: werkzeug
Requires-Dist: flask-logconfig (>=0.4.2)
